.cython-lint.toml
.ruff.toml
CHANGES.rst
DESCRIPTION.rst
LICENSE.rst
MANIFEST.in
README.rst
pyproject.toml
setup.cfg
setup.py
conf/__init__.py
conf/confpetsc.py
conf/cyautodoc.py
conf/cythonize.py
conf/cythonize.sh
conf/epydoc.cfg
conf/epydocify.py
conf/stubgen.py
demo/hpddm/hpddm.py
demo/hpddm/saddle_point.py
demo/legacy/makefile
demo/legacy/binary-io/makefile
demo/legacy/binary-io/matvecio.py
demo/legacy/bratu2d/bratu2d.py
demo/legacy/bratu2d/bratu2df90.f90
demo/legacy/bratu2d/bratu2dnpy.py
demo/legacy/bratu2d/makefile
demo/legacy/bratu3d/bratu3d.py
demo/legacy/bratu3d/makefile
demo/legacy/dmplex/anisotropic_adaptation.py
demo/legacy/dmplex/distribute_field.py
demo/legacy/dmplex/isotropic_adaptation.py
demo/legacy/kspsolve/makefile
demo/legacy/kspsolve/petsc-cg.py
demo/legacy/kspsolve/petsc-ksp.py
demo/legacy/kspsolve/petsc-mat.py
demo/legacy/kspsolve/test_mat_cg.py
demo/legacy/kspsolve/test_mat_ksp.py
demo/legacy/ode/bouncing_ball.py
demo/legacy/ode/ce.py
demo/legacy/ode/fastslowsplit.py
demo/legacy/ode/heat.py
demo/legacy/ode/orego.py
demo/legacy/ode/rober.py
demo/legacy/ode/vanderpol.py
demo/legacy/perftest/App.f90
demo/legacy/perftest/App.pyf
demo/legacy/perftest/driver.c
demo/legacy/perftest/driver.py
demo/legacy/perftest/makefile
demo/legacy/perftest/makefile.f2py
demo/legacy/perftest/makefile.petsc
demo/legacy/petsc-examples/makefile
demo/legacy/petsc-examples/ksp/ex2.py
demo/legacy/petsc-examples/ksp/ex23.py
demo/legacy/petsc-examples/ksp/makefile
demo/legacy/poisson2d/makefile
demo/legacy/poisson2d/poisson2d.py
demo/legacy/poisson3d/del2lib.f90
demo/legacy/poisson3d/del2mat.h
demo/legacy/poisson3d/del2mat.py
demo/legacy/poisson3d/makefile
demo/legacy/poisson3d/makefile.petsc
demo/legacy/poisson3d/poisson3d.c
demo/legacy/poisson3d/poisson3d.py
demo/legacy/taosolve/chwirut.py
demo/legacy/taosolve/rosenbrock.py
demo/legacy/wrap-cython/Bratu3D.pyx
demo/legacy/wrap-cython/Bratu3Dimpl.c
demo/legacy/wrap-cython/Bratu3Dimpl.h
demo/legacy/wrap-cython/makefile
src/petsc4py.egg-info/PKG-INFO
src/petsc4py.egg-info/SOURCES.txt
src/petsc4py.egg-info/dependency_links.txt
src/petsc4py.egg-info/not-zip-safe
src/petsc4py.egg-info/requires.txt
src/petsc4py.egg-info/top_level.txt
