Metadata-Version: 2.1
Name: petsc4py
Version: 3.24.4
Summary: PETSc for Python
Home-page: https://gitlab.com/petsc/petsc
Download-URL: https://pypi.io/packages/source/p/petsc4py/petsc4py-3.24.4.tar.gz
Author: Lisandro Dalcin
Author-email: dalcinl@gmail.com
Maintainer: PETSc Team
Maintainer-email: petsc-maint@mcs.anl.gov
License: BSD-2-Clause
Keywords: scientific computing,parallel computing,MPI,PETSc
Platform: POSIX
Platform: Linux
Platform: macOS
Platform: FreeBSD
Classifier: Operating System :: POSIX
Classifier: Intended Audience :: Developers
Classifier: Intended Audience :: Science/Research
Classifier: Programming Language :: C
Classifier: Programming Language :: C++
Classifier: Programming Language :: Cython
Classifier: Programming Language :: Python
Classifier: Programming Language :: Python :: 3
Classifier: Programming Language :: Python :: Implementation :: CPython
Classifier: Topic :: Scientific/Engineering
Classifier: Topic :: Software Development :: Libraries :: Python Modules
Classifier: Development Status :: 5 - Production/Stable
Requires: numpy
License-File: LICENSE.rst
Requires-Dist: numpy
